sqs_worker/__init__.py
sqs_worker/exceptions.py
sqs_worker/models.py
sqs_worker/worker.py
sqs_worker-0.3.0.dist-info/METADATA
sqs_worker-0.3.0.dist-info/WHEEL
sqs_worker-0.3.0.dist-info/licenses/LICENSE
sqs_worker-0.3.0.dist-info/RECORD
