Metadata-Version: 2.4
Name: sqs-worker
Version: 0.3.0
Summary: Manage workers triggered by AWS SQS messages
Project-URL: Homepage, https://github.com/badihio/sqs-worker
Project-URL: Repository, https://github.com/badihio/sqs-worker
Project-URL: Issues, https://github.com/badihio/sqs-worker/issues
Author: badihio
License-Expression: GPL-3.0-or-later
License-File: LICENSE
Keywords: aws,message,queue,sqs,worker
Classifier: Development Status :: 3 - Alpha
Classifier: Intended Audience :: Developers
Classifier: License :: OSI Approved :: GNU General Public License v3 or later (GPLv3+)
Classifier: Operating System :: OS Independent
Classifier: Programming Language :: Python :: 3
Classifier: Programming Language :: Python :: 3.12
Classifier: Topic :: Software Development :: Libraries :: Python Modules
Classifier: Topic :: System :: Distributed Computing
Requires-Python: >=3.12
Requires-Dist: boto3-stubs[sqs]>=1.40.26
Requires-Dist: boto3>=1.40.27
Requires-Dist: obsv-tools>=0.1.0
Requires-Dist: pydantic>=2.11.7
